preprocessing_pgp/__init__.py
preprocessing_pgp/__main__.py
preprocessing_pgp/accent_typing_formatter.py
preprocessing_pgp/const.py
preprocessing_pgp/utils.py
preprocessing_pgp/address/__init__.py
preprocessing_pgp/address/const.py
preprocessing_pgp/address/extractor.py
preprocessing_pgp/address/level_extractor.py
preprocessing_pgp/address/loc_process.py
preprocessing_pgp/address/preprocess.py
preprocessing_pgp/address/utils.py
preprocessing_pgp/card/__init__.py
preprocessing_pgp/card/const.py
preprocessing_pgp/card/preprocess.py
preprocessing_pgp/card/utils.py
preprocessing_pgp/card/validation.py
preprocessing_pgp/data/.DS_Store
preprocessing_pgp/data/location_dict_code.parquet
preprocessing_pgp/data/location_dict_code_new.parquet
preprocessing_pgp/data/location_dict_enrich_address.parquet
preprocessing_pgp/data/mobi_head_code.parquet
preprocessing_pgp/data/new_codes.parquet
preprocessing_pgp/data/new_region_code.parquet
preprocessing_pgp/data/old_codes.parquet
preprocessing_pgp/data/tele_head_code.parquet
preprocessing_pgp/data/address/city_dict.parquet
preprocessing_pgp/data/address/district_dict.parquet
preprocessing_pgp/data/address/ward_dict.parquet
preprocessing_pgp/data/email_info/dob_dict.parquet
preprocessing_pgp/data/email_info/logistic_pipeline.pkl
preprocessing_pgp/data/email_info/norm_name_trace_dict.parquet
preprocessing_pgp/data/gender_model/.DS_Store
preprocessing_pgp/data/gender_model/lstm/gender_lstm_v0.1.h5
preprocessing_pgp/data/gender_model/lstm/gender_lstm_v1.0.h5
preprocessing_pgp/data/gender_model/lstm/tokenizer.pkl
preprocessing_pgp/data/gender_model/lstm/tokenizer_bk.pkl
preprocessing_pgp/data/gender_model/rule_base/pronoun_gender_dict.parquet
preprocessing_pgp/data/name_split/ext_data.parquet
preprocessing_pgp/data/name_split/ext_data_uit.parquet
preprocessing_pgp/data/name_split/lastname_is_firstname.parquet
preprocessing_pgp/data/name_split/name_elements.parquet
preprocessing_pgp/data/name_split/nicknames.parquet
preprocessing_pgp-0.2.10.post1.dist-info/LICENSE.txt
preprocessing_pgp-0.2.10.post1.dist-info/METADATA
preprocessing_pgp-0.2.10.post1.dist-info/WHEEL
preprocessing_pgp-0.2.10.post1.dist-info/entry_points.txt
preprocessing_pgp-0.2.10.post1.dist-info/top_level.txt
preprocessing_pgp-0.2.10.post1.dist-info/RECORD
