Metadata-Version: 2.1
Name: preprocessing-pgp
Version: 0.2.10.post1
Summary: Preprocessing required data for customer service purpose
Author-email: quangvm9 <quangvm9@fpt.com.vn>
License: MIT License
Project-URL: homepage, https://github.com/quangvuminh2000/preprocessing-pgp
Keywords: nlp,text,preprocessing
Classifier: License :: OSI Approved :: MIT License
Classifier: Programming Language :: Python :: 3
Requires-Python: >=3.9
License-File: LICENSE.txt
Requires-Dist: Unidecode
Requires-Dist: tqdm
Requires-Dist: pandas
Requires-Dist: numpy
Requires-Dist: regex
Requires-Dist: flashtext
Requires-Dist: pyarrow
Requires-Dist: tensorflow >=2.8
Requires-Dist: imbalanced-learn
Requires-Dist: pickle5
Requires-Dist: rapidfuzz
Requires-Dist: dnspython
Provides-Extra: dev
Requires-Dist: black ; extra == 'dev'
Requires-Dist: bumpver ; extra == 'dev'
Requires-Dist: isort ; extra == 'dev'
Requires-Dist: pip-tools ; extra == 'dev'
Requires-Dist: pytest ; extra == 'dev'
Requires-Dist: build ; extra == 'dev'
Requires-Dist: twine ; extra == 'dev'
Requires-Dist: autopep8 ; extra == 'dev'
Requires-Dist: pylint ; extra == 'dev'
